fiopiogeos/__init__.py
fiopiogeos/common.py
fiopiogeos/fiopiogeos.py
fiopiogeos-0.0.1.dist-info/LICENSE
fiopiogeos-0.0.1.dist-info/METADATA
fiopiogeos-0.0.1.dist-info/WHEEL
fiopiogeos-0.0.1.dist-info/entry_points.txt
fiopiogeos-0.0.1.dist-info/top_level.txt
fiopiogeos-0.0.1.dist-info/RECORD
